ovos_audio_transformer_plugin_speechbrain_langdetect/__init__.py
ovos_audio_transformer_plugin_speechbrain_langdetect/version.py
ovos_audio_transformer_plugin_speechbrain_langdetect-0.0.1.dist-info/licenses/LICENSE
ovos_audio_transformer_plugin_speechbrain_langdetect-0.0.1.dist-info/METADATA
ovos_audio_transformer_plugin_speechbrain_langdetect-0.0.1.dist-info/WHEEL
ovos_audio_transformer_plugin_speechbrain_langdetect-0.0.1.dist-info/entry_points.txt
ovos_audio_transformer_plugin_speechbrain_langdetect-0.0.1.dist-info/top_level.txt
ovos_audio_transformer_plugin_speechbrain_langdetect-0.0.1.dist-info/zip-safe
ovos_audio_transformer_plugin_speechbrain_langdetect-0.0.1.dist-info/RECORD
