Metadata-Version: 2.4
Name: ovos-audio-transformer-plugin-speechbrain-langdetect
Version: 0.0.1
Summary: A speech lang detection plugin for mycroft
Home-page: https://github.com/OpenVoiceOS/ovos-audio-transformer-plugin-speechbrain-langdetect
Author: JarbasAi
Author-email: jarbasai@mailfence.com
License: Apache-2.0
Keywords: ovos plugin
Classifier: Development Status :: 3 - Alpha
Classifier: Intended Audience :: Developers
Classifier: License :: OSI Approved :: Apache Software License
License-File: LICENSE
Requires-Dist: torchaudio>=2.1.0
Requires-Dist: speechbrain>=1.0.3
Requires-Dist: ovos-plugin-manager<3.0.0,>=2.1.1
Requires-Dist: ovos-utils<1.0.0,>=0.8.4
Requires-Dist: ovos-config>=0.0.12
Requires-Dist: huggingface_hub==0.36.0
Dynamic: author
Dynamic: author-email
Dynamic: classifier
Dynamic: home-page
Dynamic: keywords
Dynamic: license
Dynamic: license-file
Dynamic: requires-dist
Dynamic: summary
